rlogging/__init__.py
rlogging/__init__.pyi
rlogging/logs.py
rlogging/logs.pyi
rlogging/prometheus.py
rlogging/prometheus.pyi
rlogging/sentry.py
rlogging/sentry.pyi
rlogging/settings.py
rlogging/settings.pyi
rlogging/telemetry.py
rlogging/telemetry.pyi
rlogging/utils.py
rlogging/utils.pyi
rlogging/extension/__init__.py
rlogging/extension/__init__.pyi
rlogging/extension/adapters.py
rlogging/extension/adapters.pyi
rlogging/extension/filters.py
rlogging/extension/filters.pyi
rlogging/extension/formatters.py
rlogging/extension/formatters.pyi
rlogging/extension/handlers.py
rlogging/extension/handlers.pyi
rlogging/extension/namespaces.py
rlogging/extension/namespaces.pyi
rlogging/integration/__init__.py
rlogging/integration/__init__.pyi
rlogging/integration/aiogram/__init__.py
rlogging/integration/aiogram/__init__.pyi
rlogging/integration/django/__init__.py
rlogging/integration/django/__init__.pyi
rlogging/integration/django/adapters.py
rlogging/integration/django/adapters.pyi
rlogging/integration/django/apps.py
rlogging/integration/django/apps.pyi
rlogging/integration/django/handlers.py
rlogging/integration/django/handlers.pyi
rlogging/integration/django/middleware.py
rlogging/integration/django/middleware.pyi
rlogging/integration/django/models_mixins.py
rlogging/integration/django/models_mixins.pyi
rlogging/integration/django/signals.py
rlogging/integration/django/signals.pyi
rlogging/integration/django/storages.py
rlogging/integration/django/storages.pyi
rlogging/integration/fastapi/__init__.py
rlogging/integration/fastapi/__init__.pyi
rlogging/integration/sa/__init__.py
rlogging/integration/sa/__init__.pyi
rlogging/integration/sa/connect.py
rlogging/integration/sa/connect.pyi
rlogging/integration/sa/fields.py
rlogging/integration/sa/fields.pyi
rlogging-2.0.5.dist-info/METADATA
rlogging-2.0.5.dist-info/WHEEL
rlogging-2.0.5.dist-info/licenses/LICENSE
rlogging-2.0.5.dist-info/RECORD
