Metadata-Version: 2.4
Name: rlogging
Version: 2.0.5
Summary: A set of tools to improve the observability of applications
Author-email: Aleksei Marusich <aleksei.marusich@rocshers.com>
License: MIT
License-File: LICENSE
Keywords: logging,rocshers
Classifier: Intended Audience :: Developers
Classifier: Intended Audience :: Information Technology
Classifier: Intended Audience :: System Administrators
Classifier: License :: OSI Approved :: MIT License
Classifier: Operating System :: OS Independent
Classifier: Programming Language :: Python
Classifier: Programming Language :: Python :: 3
Classifier: Programming Language :: Python :: 3 :: Only
Classifier: Programming Language :: Python :: 3.12
Classifier: Topic :: Software Development
Classifier: Topic :: Software Development :: Build Tools
Classifier: Topic :: Software Development :: Libraries
Classifier: Topic :: Software Development :: Libraries :: Python Modules
Classifier: Topic :: System :: Archiving :: Packaging
Classifier: Topic :: System :: Installation/Setup
Classifier: Topic :: System :: Software Distribution
Requires-Python: >=3.12
Provides-Extra: common
Requires-Dist: pydantic-settings>=2.6.0; extra == 'common'
Provides-Extra: django
Requires-Dist: django-storages[s3]>=1.14.4; extra == 'django'
Requires-Dist: django>=5.1.2; extra == 'django'
Provides-Extra: opentelemetry
Requires-Dist: opentelemetry-distro[otlp]>=0.48b0; extra == 'opentelemetry'
Provides-Extra: prometheus
Requires-Dist: logs-prometheus>=1.1.2; extra == 'prometheus'
Requires-Dist: prometheus-client>=0.21.0; extra == 'prometheus'
Provides-Extra: sentry
Requires-Dist: sentry-sdk>=2.17.0; extra == 'sentry'
